b_proxy/__init__.py
b_proxy/proxy.py
b_proxy-0.0.1rc1.dist-info/WHEEL
b_proxy-0.0.1rc1.dist-info/METADATA
b_proxy-0.0.1rc1.dist-info/RECORD
